evion/__init__.py
evion/client.py
evion/exceptions.py
tests/__init__.py
tests/test_client.py
tests/test_exceptions.py
evion-0.1.3.dist-info/LICENSE
evion-0.1.3.dist-info/METADATA
evion-0.1.3.dist-info/WHEEL
evion-0.1.3.dist-info/top_level.txt
evion-0.1.3.dist-info/RECORD
