Metadata-Version: 2.1
Name: evion
Version: 0.1.3
Summary: Python library for NDVI vegetation analysis using AI
Author: Evion Team
Author-email: support@evion.ai
Requires-Python: >=3.8
License-File: LICENSE
Requires-Dist: requests >=2.28.0
Requires-Dist: Pillow >=9.0.0
